{"type":"UIControl","widthType":"RELATIVE","heightType":"RELATIVE","name":"Root","children":[{"type":"UIButton","width":74,"height":28,"xAnchor":1,"align":"TOP_RIGHT","name":"btnMenu","textComponent":{"text":"Menu","font":{"align":"CENTER","padding":{},"typeFace":"segeo12.fnt"}},"scale9Component":{"padding":{"left":16,"right":16,"top":16,"bottom":16},"imageComponent":{"filename":"../textures/button.png"}}},{"type":"UIImage","height":84,"yAnchor":1,"align":"BOTTOM_LEFT","widthType":"RELATIVE","name":"bottomPanel","children":[{"type":"UIControl","y":19,"width":192,"height":48,"xAnchor":0.5,"yAnchor":0.5,"align":"CENTER","name":"abilityGroup","children":[{"type":"UIButton","width":48,"height":48,"yAnchor":0.5,"align":"LEFT","name":"btnAbility1","children":[{"type":"UIPanel","x":6,"y":6,"width":12,"height":12,"clickThrough":true,"children":[{"type":"UILabel","width":1,"height":1,"widthType":"PERCENTAGE","heightType":"PERCENTAGE","textComponent":{"text":"1","font":{"align":"CENTER","padding":{},"typeFace":"segeo12.fnt"}}}],"color":"5f5f5fff"}],"textComponent":{"font":{"align":"CENTER","padding":{}}},"scale9Component":{"padding":{"left":16,"right":16,"top":16,"bottom":16},"imageComponent":{"filename":"../textures/button.png"}}},{"type":"UIButton","x":48,"width":48,"height":48,"yAnchor":0.5,"align":"LEFT","name":"btnAbility2","children":[{"type":"UIPanel","x":6,"y":6,"width":12,"height":12,"clickThrough":true,"children":[{"type":"UILabel","width":1,"height":1,"widthType":"PERCENTAGE","heightType":"PERCENTAGE","textComponent":{"text":"2","font":{"align":"CENTER","padding":{},"typeFace":"segeo12.fnt"}}}],"color":"5f5f5fff"}],"textComponent":{"font":{"align":"CENTER","padding":{}}},"scale9Component":{"padding":{"left":16,"right":16,"top":16,"bottom":16},"imageComponent":{"filename":"../textures/button.png"}}},{"type":"UIButton","x":96,"width":48,"height":48,"yAnchor":0.5,"align":"LEFT","name":"btnAbility3","children":[{"type":"UIPanel","x":6,"y":6,"width":12,"height":12,"clickThrough":true,"children":[{"type":"UILabel","width":1,"height":1,"widthType":"PERCENTAGE","heightType":"PERCENTAGE","textComponent":{"text":"3","font":{"align":"CENTER","padding":{},"typeFace":"segeo12.fnt"}}}],"color":"5f5f5fff"}],"textComponent":{"font":{"align":"CENTER","padding":{}}},"scale9Component":{"padding":{"left":16,"right":16,"top":16,"bottom":16},"imageComponent":{"filename":"../textures/button.png"}}},{"type":"UIButton","x":144,"width":48,"height":48,"yAnchor":0.5,"align":"LEFT","name":"btnAbility4","children":[{"type":"UIPanel","x":6,"y":6,"width":12,"height":12,"clickThrough":true,"children":[{"type":"UILabel","width":1,"height":1,"widthType":"PERCENTAGE","heightType":"PERCENTAGE","textComponent":{"text":"4","font":{"align":"CENTER","padding":{},"typeFace":"segeo12.fnt"}}}],"color":"5f5f5fff"}],"textComponent":{"font":{"align":"CENTER","padding":{}}},"scale9Component":{"padding":{"left":16,"right":16,"top":16,"bottom":16},"imageComponent":{"filename":"../textures/button.png"}}}]}],"scale9Component":{"padding":{"left":38,"right":38,"top":72},"imageComponent":{"filename":"../textures/bottomFrame.png"},"repeat":true}}]}